crontab_win/__init__.py
crontab_win/__main__.py
crontab_win/app.py
crontab_win/cli.py
crontab_win-0.0.2.dist-info/licenses/LICENSE
crontab_win-0.0.2.dist-info/METADATA
crontab_win-0.0.2.dist-info/WHEEL
crontab_win-0.0.2.dist-info/entry_points.txt
crontab_win-0.0.2.dist-info/top_level.txt
crontab_win-0.0.2.dist-info/RECORD
