Metadata-Version: 2.4
Name: crontab-win
Version: 0.0.2
Summary: crontab for windows
Author: sukhbinder singh
License: Apache-2.0
Project-URL: Homepage, https://github.com/sukhbinder/crontab-win
Project-URL: Changelog, https://github.com/sukhbinder/crontab-win/releases
Project-URL: Issues, https://github.com/sukhbinder/crontab-win/issues
Project-URL: CI, https://github.com/sukhbinder/crontab-win/actions
Classifier: License :: OSI Approved :: Apache Software License
Requires-Python: >=3.8
License-File: LICENSE
Requires-Dist: click
Provides-Extra: test
Requires-Dist: pytest; extra == "test"
Dynamic: license-file
